src/tablify_anomaly-true/__init__.py
src/tablify_anomaly-true/main.py
tablify_anomaly_true-1.0.0.dist-info/METADATA
tablify_anomaly_true-1.0.0.dist-info/WHEEL
tablify_anomaly_true-1.0.0.dist-info/licenses/LICENSE
tablify_anomaly_true-1.0.0.dist-info/RECORD
