Metadata-Version: 2.1
Name: tablify_anomaly-true
Version: 1.0.0
Summary: A lightweight formatting package that converts lists & dictionaries to easy to read tables.
Project-URL: Homepage, https://github.com/anomaly-true/Tablify
Author-email: Anomaly <benpraha99@gmail.com>
License: MIT License
Classifier: License :: OSI Approved :: MIT License
Classifier: Operating System :: OS Independent
Classifier: Programming Language :: Python :: 3
Requires-Python: >=3.7
